README.txt
setup.cfg
setup.py
docs/HISTORY.txt
docs/INSTALL.txt
docs/LICENSE.GPL
docs/LICENSE.txt
slc/__init__.py
slc.autocategorize.egg-info/PKG-INFO
slc.autocategorize.egg-info/SOURCES.txt
slc.autocategorize.egg-info/dependency_links.txt
slc.autocategorize.egg-info/entry_points.txt
slc.autocategorize.egg-info/namespace_packages.txt
slc.autocategorize.egg-info/not-zip-safe
slc.autocategorize.egg-info/paster_plugins.txt
slc.autocategorize.egg-info/requires.txt
slc.autocategorize.egg-info/top_level.txt
slc/autocategorize/README.txt
slc/autocategorize/__init__.py
slc/autocategorize/configure.zcml
slc/autocategorize/events.py
slc/autocategorize/interfaces.py
slc/autocategorize/schemaextender.py
slc/autocategorize/tests.py
slc/autocategorize/profiles/default/browserlayer.xml
slc/autocategorize/profiles/default/metadata.xml