Metadata-Version: 1.0
Name: slc.autocategorize
Version: 0.2
Summary: Automatically inherit the parent folder's categories when you create an object.
Home-page: http://svn.plone.org/svn/plone/plone.example
Author: JC Brand, Syslab.com GmbH
Author-email: brand@syslab.com
License: GPL
Platform: UNKNOWN
Classifier: Framework :: Plone
Classifier: Programming Language :: Python
Classifier: Topic :: Software Development :: Libraries :: Python Modules
